[
{
	"uri": "https://liangzhongyun.github.io/basics/",
	"title": "Basics",
	"tags": [],
	"description": "",
	"content": "Chapter X Some Chapter title Lorem Ipsum.\n"
},
{
	"uri": "https://liangzhongyun.github.io/",
	"title": "Hugo Site",
	"tags": [],
	"description": "",
	"content": ""
},
{
	"uri": "https://liangzhongyun.github.io/basics/second-content/",
	"title": "Second Content",
	"tags": [],
	"description": "",
	"content": ""
},
{
	"uri": "https://liangzhongyun.github.io/basics/first-content/",
	"title": "First Content",
	"tags": [],
	"description": "",
	"content": "h1 Test h2 test h3 test h4 test "
},
{
	"uri": "https://liangzhongyun.github.io/categories/",
	"title": "Categories",
	"tags": [],
	"description": "",
	"content": ""
},
{
	"uri": "https://liangzhongyun.github.io/tags/",
	"title": "Tags",
	"tags": [],
	"description": "",
	"content": ""
}]